MANIFEST.in
README.md
img.png
img_1.png
setup.py
test.ipynb
test.pdb
test.py
easy3dmol/__init__.py
easy3dmol/type.py
easy3dmol/utils.py
easy3dmol.egg-info/PKG-INFO
easy3dmol.egg-info/SOURCES.txt
easy3dmol.egg-info/dependency_links.txt
easy3dmol.egg-info/top_level.txt